snowjob-0.0.4.data/scripts/snowjob
snowjob/__init__.py
snowjob-0.0.4.dist-info/METADATA
snowjob-0.0.4.dist-info/entry_points.txt
snowjob-0.0.4.dist-info/pydist.json
snowjob-0.0.4.dist-info/DESCRIPTION.rst
snowjob-0.0.4.dist-info/RECORD
snowjob-0.0.4.dist-info/WHEEL
snowjob-0.0.4.dist-info/top_level.txt
