Metadata-Version: 1.1
Name: snowjob
Version: 0.0.4
Summary: A python script that will make your terminal snow
Home-page: http://github.com/sontek/snowjob
Author: John Anderson
Author-email: sontek@gmail.com
License: BSD
Platform: UNKNOWN
Classifier: Development Status :: 3 - Alpha
Classifier: Topic :: Utilities
Classifier: Environment :: Console
Classifier: Environment :: Console :: Curses
Classifier: License :: OSI Approved :: BSD License
